<?xml version="1.0" encoding="UTF-8"?>
<beans xmlns="http://www.springframework.org/schema/beans"
	xmlns:xsi="http://www.w3.org/2001/XMLSchema-instance"
	xmlns:p="http://www.springframework.org/schema/p"
	xsi:schemaLocation="http://www.springframework.org/schema/beans http://www.springframework.org/schema/beans/spring-beans.xsd">

	<bean id="mailSender" class="org.springframework.mail.javamail.JavaMailSenderImpl">
		<property name="javaMailProperties">
			<props>
				<prop key="mail.smtp.host">smtp.naver.com</prop>
				<prop key="mail.smtp.port">465</prop>
				<prop key="mail.smtp.auth">true</prop>
				<prop key="mail.transport.protocol">smtp</prop>
				<prop key="mail.smtp.starttls.enable">true</prop>
				<prop key="mail.smtp.ssl.trust">smtp.naver.com</prop>
				<prop key="mail.smtp.ssl.enable">true</prop>
				<prop key="mail.debug">true</prop>
			</props>
		</property>
		<property name="defaultEncoding" value="utf-8" />
		<property name="username" value="box6937510@naver.com" />
		<property name="password" value="box51655165" />
	</bean>
	<bean id="mailNotifier" class="com.spring.message.MimeAttachNotifier" p:mailSender-ref="mailSender" />
</beans>